llmtop/__init__.py
llmtop/llmtop.py
llmtop-0.1.0.dist-info/LICENSE
llmtop-0.1.0.dist-info/METADATA
llmtop-0.1.0.dist-info/WHEEL
llmtop-0.1.0.dist-info/entry_points.txt
llmtop-0.1.0.dist-info/top_level.txt
llmtop-0.1.0.dist-info/RECORD
