Metadata-Version: 2.2
Name: llmtop
Version: 0.1.0
Summary: LLM-powered system monitoring with real-time performance insights
Author: Arinbjörn Kolbeinsson
Classifier: Development Status :: 4 - Beta
Classifier: Programming Language :: Python :: 3
Classifier: Programming Language :: Python :: 3.8
Classifier: Programming Language :: Python :: 3.9
Classifier: Programming Language :: Python :: 3.10
Classifier: Programming Language :: Python :: 3.11
Classifier: Operating System :: OS Independent
Classifier: Topic :: System :: Monitoring
Requires-Python: >=3.8
License-File: LICENSE
Requires-Dist: rich>=13.7.0
Requires-Dist: psutil>=5.9.0
Requires-Dist: GPUtil>=1.4.0
Requires-Dist: openai>=1.12.0
Requires-Dist: ollama>=0.1.6
Requires-Dist: python-dateutil>=2.8.2
Requires-Dist: typing-extensions>=4.9.0
Dynamic: author
Dynamic: classifier
Dynamic: description
Dynamic: description-content-type
Dynamic: requires-dist
Dynamic: requires-python
Dynamic: summary
